pyglodon/__init__.py
pyglodon/lx.py
pyglodon/pre_picture.py
pyglodon/transformer_utils.py
pyglodon-1.0.7.dist-info/LICENSE
pyglodon-1.0.7.dist-info/METADATA
pyglodon-1.0.7.dist-info/WHEEL
pyglodon-1.0.7.dist-info/top_level.txt
pyglodon-1.0.7.dist-info/RECORD
